<?xml version="1.0" encoding="utf-8" ?>
<dwsync>
<file name="1.jpg" server="lophoctiengnhat.com/tanminhgiang.tk/" local="130491548590135628" remote="130491580800000000" Dst="0" />
<file name="10.jpg" server="lophoctiengnhat.com/tanminhgiang.tk/" local="130491590188144898" remote="130492685400000000" Dst="0" />
<file name="12.jpg" server="lophoctiengnhat.com/tanminhgiang.tk/" local="130491589967202261" remote="130492685400000000" Dst="0" />
<file name="13.jpg" server="lophoctiengnhat.com/tanminhgiang.tk/" local="130491588784154594" remote="130492685400000000" Dst="0" />
<file name="11.jpg" server="lophoctiengnhat.com/tanminhgiang.tk/" local="130491591466508016" remote="130492685400000000" Dst="0" />
<file name="14.jpeg" server="lophoctiengnhat.com/tanminhgiang.tk/" local="130491592822235559" remote="130492685400000000" Dst="0" />
<file name="16.jpg" server="lophoctiengnhat.com/tanminhgiang.tk/" local="130491594787287954" remote="130492685400000000" Dst="0" />
<file name="17.jpg" server="lophoctiengnhat.com/tanminhgiang.tk/" local="130492034919478759" remote="130492685400000000" Dst="0" />
<file name="2.jpg" server="lophoctiengnhat.com/tanminhgiang.tk/" local="130491591318169531" remote="130492685400000000" Dst="0" />
<file name="15.jpg" server="lophoctiengnhat.com/tanminhgiang.tk/" local="130491593928608840" remote="130492685400000000" Dst="0" />
<file name="3.jpg" server="lophoctiengnhat.com/tanminhgiang.tk/" local="130491589673675472" remote="130492685400000000" Dst="0" />
<file name="6.jpg" server="lophoctiengnhat.com/tanminhgiang.tk/" local="130491591621536883" remote="130492685400000000" Dst="0" />
<file name="4.jpg" server="lophoctiengnhat.com/tanminhgiang.tk/" local="130491588567432198" remote="130492685400000000" Dst="0" />
<file name="5.jpg" server="lophoctiengnhat.com/tanminhgiang.tk/" local="130491589399359782" remote="130492685400000000" Dst="0" />
<file name="7.jpg" server="lophoctiengnhat.com/tanminhgiang.tk/" local="130491592106684632" remote="130492685400000000" Dst="0" />
<file name="8.jpg" server="lophoctiengnhat.com/tanminhgiang.tk/" local="130491589234830371" remote="130492685400000000" Dst="0" />
<file name="9.jpg" server="lophoctiengnhat.com/tanminhgiang.tk/" local="130491592724429965" remote="130492685400000000" Dst="0" />
<file name="frogs(2).swf" server="lophoctiengnhat.com/tanminhgiang.tk/" local="130492199594817649" remote="130492685400000000" Dst="0" />
</dwsync>